{
  "name": "Alpha Saurus",
  "mass": 1.989e+30,
  "position": {
    "x": 230.6,
    "y": 228.5
  },
  "bodies": [
    {
      "position": {
        "x": 2479.3647291047423,
        "y": -1286.5212682119263
      },
      "name": "I",
      "distance_from_parent": 406725000,
      "diameter": 3189,
      "gravity": 2.45,
      "length_of_day": 26.6,
      "mass": 0,
      "type": "Infrared",
      "bioHazard": "NONE",
      "weatherHazard": "LOW",
      "tectonicsHazard": "LOW",
      "thermalHazard": "NONE",
      "orbital_period": 1636.195696489731
    },
    {
      "position": {
        "x": -3818.4317635713323,
        "y": 2182.338398552928
      },
      "name": "II",
      "distance_from_parent": 674368750,
      "diameter": 3571.6800000000003,
      "gravity": 5.292000000000001,
      "length_of_day": 17.5,
      "mass": 0,
      "type": "Super-Dense",
      "bioHazard": "SEVERE",
      "weatherHazard": "LOW",
      "tectonicsHazard": "INSTANT_DEATH",
      "thermalHazard": "NONE",
      "orbital_period": 3493.2534758904817
    },
    {
      "position": {
        "x": -3915.303338121514,
        "y": -11172.719700171465
      },
      "name": "III",
      "distance_from_parent": 1819743750,
      "diameter": 4081.92,
      "gravity": 0.9800000000000001,
      "length_of_day": 20.5,
      "mass": 0,
      "type": "Noble",
      "bioHazard": "HIGH",
      "weatherHazard": "NONE",
      "tectonicsHazard": "LOW",
      "thermalHazard": "NONE",
      "orbital_period": 15484.575323073412
    }
  ]
}