{
  "name": "Beta Tucanae",
  "mass": 3e+24,
  "position": {
    "x": 393.7,
    "y": 562.5
  },
  "bodies": [
    {
      "position": {
        "x": 1028.3335963153293,
        "y": -305.48776542522296
      },
      "name": "I",
      "distance_from_parent": 161287500,
      "diameter": 3189,
      "gravity": 1.3720000000000003,
      "length_of_day": 20.1,
      "mass": 0,
      "orbital_period": 0
    },
    {
      "position": {
        "x": 3174.6966162595963,
        "y": 4701.691015741738
      },
      "name": "II",
      "distance_from_parent": 748000000,
      "diameter": 178839.12,
      "gravity": 28.812,
      "length_of_day": 8.1,
      "mass": 0,
      "orbital_period": 0
    },
    {
      "position": {
        "x": 4800.114918802427,
        "y": -5976.564223913579
      },
      "name": "III",
      "distance_from_parent": 1182775000,
      "diameter": 3189,
      "gravity": 2.45,
      "length_of_day": 27.1,
      "mass": 0,
      "orbital_period": 0
    },
    {
      "position": {
        "x": -2120.87393434665,
        "y": -10791.442599714455
      },
      "name": "IV",
      "distance_from_parent": 1744359375,
      "diameter": 172078.44,
      "gravity": 27.734,
      "length_of_day": 15.9,
      "mass": 0,
      "orbital_period": 0
    },
    {
      "position": {
        "x": 1962.2588441319783,
        "y": -14152.457842224258
      },
      "name": "V",
      "distance_from_parent": 2219748437.5,
      "diameter": 4464.599999999999,
      "gravity": 6.86,
      "length_of_day": 19.2,
      "mass": 0,
      "orbital_period": 0
    },
    {
      "position": {
        "x": 3305.2740740961817,
        "y": 4674.722417655955
      },
      "name": "II-a",
      "distance_from_parent": 7480000,
      "diameter": 3316.56,
      "gravity": 0.784,
      "length_of_day": 24.5,
      "parent": "II",
      "mass": 0,
      "orbital_period": 0
    },
    {
      "position": {
        "x": 3178.967777152183,
        "y": 4568.42611052507
      },
      "name": "II-b",
      "distance_from_parent": 7480000,
      "diameter": 3189,
      "gravity": 1.47,
      "length_of_day": 19.8,
      "parent": "II",
      "mass": 0,
      "orbital_period": 0
    },
    {
      "position": {
        "x": 3195.003026381686,
        "y": 4833.468963387508
      },
      "name": "II-c",
      "distance_from_parent": 7480000,
      "diameter": 4719.72,
      "gravity": 2.2540000000000004,
      "length_of_day": 16.5,
      "parent": "II",
      "mass": 0,
      "orbital_period": 0
    },
    {
      "position": {
        "x": -2042.0466814688348,
        "y": -10898.978835381857
      },
      "name": "IV-a",
      "distance_from_parent": 17443593.75,
      "diameter": 4209.4800000000005,
      "gravity": 4.606,
      "length_of_day": 21.8,
      "parent": "IV",
      "mass": 0,
      "orbital_period": 0
    },
    {
      "position": {
        "x": -2140.3916862900182,
        "y": -10923.33966236884
      },
      "name": "IV-b",
      "distance_from_parent": 17443593.75,
      "diameter": 3316.56,
      "gravity": 2.352,
      "length_of_day": 3298.9,
      "parent": "IV",
      "mass": 0,
      "orbital_period": 0
    }
  ]
}