{
  "name": "Beta Librae",
  "mass": 1.989e+30,
  "position": {
    "x": 741.4,
    "y": 912.4
  },
  "bodies": [
    {
      "position": {
        "x": -76.03762772712446,
        "y": -363.71630715093727
      },
      "name": "Vlik",
      "distance_from_parent": 227321875,
      "diameter": 11480.4,
      "gravity": 8.428,
      "length_of_day": 20,
      "mass": 0,
      "type": "Water",
      "orbital_period": 683.6688437464342
    },
    {
      "position": {
        "x": -7.868937951654971,
        "y": -373.60644183433783
      },
      "name": "Vlik-a",
      "distance_from_parent": 2273218.75,
      "diameter": 4464.599999999999,
      "gravity": 7.056,
      "length_of_day": 17.8,
      "parent": "Vlik",
      "mass": 0,
      "type": "Super-Dense",
      "orbital_period": 0.6836688437464342
    },
    {
      "position": {
        "x": -27.767221742654264,
        "y": -412.8564428432044
      },
      "name": "Vlik-b",
      "distance_from_parent": 2273218.75,
      "diameter": 4337.04,
      "gravity": 5.096000000000001,
      "length_of_day": 22.7,
      "parent": "Vlik",
      "mass": 0,
      "type": "Lanthanide",
      "orbital_period": 0.6836688437464342
    }
  ]
}