{
  "name": "Delta Crucis",
  "mass": 1.989e+30,
  "position": {
    "x": 543.7,
    "y": 591.6
  },
  "bodies": [
    {
      "position": {
        "x": 7267.93445820301,
        "y": -8295.137503273732
      },
      "name": "I",
      "distance_from_parent": 1671604687.5,
      "diameter": 76663.56,
      "gravity": 11.76,
      "length_of_day": 14.3,
      "mass": 0,
      "type": "Gas Giant",
      "bioHazard": "NONE",
      "weatherHazard": "INSTANT_DEATH",
      "tectonicsHazard": "MINIMUM",
      "thermalHazard": "NONE",
      "orbital_period": 13632.776499230322
    },
    {
      "position": {
        "x": 8958.903855383664,
        "y": -10882.889255172211
      },
      "name": "II",
      "distance_from_parent": 2134429687.5,
      "diameter": 150903.48,
      "gravity": 24.304000000000002,
      "length_of_day": 10.5,
      "mass": 0,
      "type": "Gas Giant",
      "bioHazard": "NONE",
      "weatherHazard": "INSTANT_DEATH",
      "tectonicsHazard": "MINIMUM",
      "thermalHazard": "NONE",
      "orbital_period": 19670.10705313973
    },
    {
      "position": {
        "x": 6946.468056278573,
        "y": -8624.139333027317
      },
      "name": "I-a",
      "distance_from_parent": 16716046.875,
      "diameter": 4719.72,
      "gravity": 3.724,
      "length_of_day": 28.6,
      "parent": "I",
      "mass": 0,
      "type": "Green",
      "bioHazard": "NONE",
      "weatherHazard": "MINIMUM",
      "tectonicsHazard": "SEVERE",
      "thermalHazard": "NONE",
      "orbital_period": 13.632776499230323
    },
    {
      "position": {
        "x": 6819.805845176341,
        "y": -8398.885263414586
      },
      "name": "I-b",
      "distance_from_parent": 16716046.875,
      "diameter": 3571.6800000000003,
      "gravity": 2.7440000000000007,
      "length_of_day": 26.3,
      "parent": "I",
      "mass": 0,
      "type": "Acid",
      "bioHazard": "NONE",
      "weatherHazard": "NONE",
      "tectonicsHazard": "LOW",
      "thermalHazard": "NONE",
      "orbital_period": 13.632776499230323
    },
    {
      "position": {
        "x": 7537.276264078152,
        "y": -7922.259717457298
      },
      "name": "I-c",
      "distance_from_parent": 16716046.875,
      "diameter": 3444.1200000000003,
      "gravity": 2.6460000000000004,
      "length_of_day": 20.5,
      "parent": "I",
      "mass": 0,
      "type": "Acid",
      "bioHazard": "NONE",
      "weatherHazard": "NONE",
      "tectonicsHazard": "MINIMUM",
      "thermalHazard": "NONE",
      "orbital_period": 13.632776499230323
    },
    {
      "position": {
        "x": 7506.962544535386,
        "y": -7902.138234200962
      },
      "name": "I-d",
      "distance_from_parent": 16716046.875,
      "diameter": 4209.4800000000005,
      "gravity": 6.174,
      "length_of_day": 28.1,
      "parent": "I",
      "mass": 0,
      "type": "Super-Dense",
      "bioHazard": "MODERATE",
      "weatherHazard": "MINIMUM",
      "tectonicsHazard": "EXTREME",
      "thermalHazard": "NONE",
      "orbital_period": 13.632776499230323
    },
    {
      "position": {
        "x": 9050.918384509634,
        "y": -9982.156055845297
      },
      "name": "II-a",
      "distance_from_parent": 21344296.875,
      "diameter": 3316.56,
      "gravity": 1.47,
      "length_of_day": 2929.2,
      "parent": "II",
      "mass": 0,
      "type": "Pellucid",
      "bioHazard": "NONE",
      "weatherHazard": "NONE",
      "tectonicsHazard": "NONE",
      "thermalHazard": "NONE",
      "orbital_period": 19.670107053139734
    }
  ],
  "objects": []
}