{
  "name": "Delta Gorno",
  "mass": 1.989e+30,
  "position": {
    "x": 290.8,
    "y": 26.9
  },
  "bodies": [
    {
      "position": {
        "x": 85.02825529088256,
        "y": 1893.3831990891704
      },
      "name": "Kyabetsu",
      "distance_from_parent": 281668750,
      "diameter": 3826.7999999999997,
      "gravity": 1.764,
      "length_of_day": 16.2,
      "mass": 0,
      "type": "Selenic",
      "bioHazard": "NONE",
      "weatherHazard": "LOW",
      "tectonicsHazard": "LOW",
      "thermalHazard": "MINIMUM",
      "orbital_period": 942.9571197765823
    },
    {
      "position": {
        "x": -3743.241869437793,
        "y": 1438.022668530344
      },
      "name": "II",
      "distance_from_parent": 641059375,
      "diameter": 4209.4800000000005,
      "gravity": 1.862,
      "length_of_day": 27.2,
      "mass": 0,
      "type": "Selenic",
      "bioHazard": "NONE",
      "weatherHazard": "NONE",
      "tectonicsHazard": "LOW",
      "thermalHazard": "NONE",
      "orbital_period": 3237.6606577803936
    },
    {
      "position": {
        "x": 5705.710167994556,
        "y": -29.92575078199409
      },
      "name": "III",
      "distance_from_parent": 812281250,
      "diameter": 3571.6800000000003,
      "gravity": 1.6660000000000001,
      "length_of_day": 1969.2,
      "mass": 0,
      "type": "Selenic",
      "bioHazard": "NONE",
      "weatherHazard": "NONE",
      "tectonicsHazard": "NONE",
      "thermalHazard": "NONE",
      "orbital_period": 4617.890035928743
    },
    {
      "position": {
        "x": -4840.146667478774,
        "y": -3526.271479272208
      },
      "name": "IV",
      "distance_from_parent": 936168750,
      "diameter": 3826.7999999999997,
      "gravity": 4.41,
      "length_of_day": 19,
      "mass": 0,
      "type": "Metal",
      "bioHazard": "SEVERE",
      "weatherHazard": "LOW",
      "tectonicsHazard": "MODERATE",
      "thermalHazard": "NONE",
      "orbital_period": 5713.670009117268
    },
    {
      "position": {
        "x": -2106.923340024991,
        "y": -8790.586334776743
      },
      "name": "V",
      "distance_from_parent": 1370651562.5,
      "diameter": 3826.7999999999997,
      "gravity": 4.508000000000001,
      "length_of_day": 29.7,
      "mass": 0,
      "type": "Metal",
      "bioHazard": "MINIMUM",
      "weatherHazard": "LOW",
      "tectonicsHazard": "LOW",
      "thermalHazard": "NONE",
      "orbital_period": 10122.191340680032
    },
    {
      "position": {
        "x": 10656.726330108457,
        "y": 2832.3917319313528
      },
      "name": "VI",
      "distance_from_parent": 1610829687.5,
      "diameter": 4719.72,
      "gravity": 5.684,
      "length_of_day": 15.5,
      "mass": 0,
      "type": "Metal",
      "bioHazard": "NONE",
      "weatherHazard": "LOW",
      "tectonicsHazard": "LOW",
      "thermalHazard": "NONE",
      "orbital_period": 12896.099695321638
    }
  ],
  "objects": []
}