{
  "name": "Delta Arietis",
  "mass": 3.978e+30,
  "position": {
    "x": 954.1,
    "y": 168.7
  },
  "bodies": [
    {
      "position": {
        "x": 7400.714648489418,
        "y": 2213.591912789712
      },
      "name": "I",
      "distance_from_parent": 1014475000,
      "diameter": 3699.24,
      "gravity": 2.94,
      "length_of_day": 23.2,
      "mass": 0,
      "type": "Chondrite",
      "bioHazard": "NONE",
      "weatherHazard": "NONE",
      "tectonicsHazard": "SEVERE",
      "thermalHazard": "NONE",
      "orbital_period": 4557.545048312749
    },
    {
      "position": {
        "x": -1347.3072348206224,
        "y": -9238.932902307824
      },
      "name": "II",
      "distance_from_parent": 1452756250,
      "diameter": 4464.599999999999,
      "gravity": 2.0580000000000003,
      "length_of_day": 15.5,
      "mass": 0,
      "type": "Dust",
      "bioHazard": "MINIMUM",
      "weatherHazard": "MINIMUM",
      "tectonicsHazard": "LOW",
      "thermalHazard": "NONE",
      "orbital_period": 7810.126627530802
    }
  ]
}