{
  "name": "Delta Giclas",
  "mass": 1.989e+30,
  "position": {
    "x": 87.7,
    "y": 34
  },
  "bodies": [
    {
      "position": {
        "x": 618.0357567724717,
        "y": 885.5328799369659
      },
      "name": "I",
      "distance_from_parent": 150476562.5,
      "diameter": 13776.480000000001,
      "gravity": 10.584000000000001,
      "length_of_day": 21.5,
      "mass": 0,
      "type": "Primordial",
      "orbital_period": 368.20292710783866
    },
    {
      "position": {
        "x": -1571.5911565304625,
        "y": 2338.931205430229
      },
      "name": "II",
      "distance_from_parent": 426009375,
      "diameter": 4719.72,
      "gravity": 5.292000000000001,
      "length_of_day": 21.9,
      "mass": 0,
      "type": "Metal",
      "orbital_period": 1753.9317066549022
    },
    {
      "position": {
        "x": 1408.895843425184,
        "y": -4442.301505713409
      },
      "name": "III",
      "distance_from_parent": 700081250,
      "diameter": 3699.24,
      "gravity": 2.7440000000000007,
      "length_of_day": 26.1,
      "mass": 0,
      "type": "Green",
      "orbital_period": 3694.9333909068378
    },
    {
      "position": {
        "x": -5537.61864935794,
        "y": 3533.2314642918536
      },
      "name": "IV",
      "distance_from_parent": 993729687.5,
      "diameter": 9822.12,
      "gravity": 7.3500000000000005,
      "length_of_day": 1241.1,
      "mass": 0,
      "type": "Water",
      "orbital_period": 6248.652034937792
    },
    {
      "position": {
        "x": -5035.610668551888,
        "y": -6062.095797074839
      },
      "name": "V",
      "distance_from_parent": 1194462500,
      "diameter": 3189,
      "gravity": 1.3720000000000003,
      "length_of_day": 26.3,
      "mass": 0,
      "type": "Purple",
      "orbital_period": 8234.604093463844
    },
    {
      "position": {
        "x": 3748.717915586327,
        "y": -8069.6332980433
      },
      "name": "VI",
      "distance_from_parent": 1333835937.5,
      "diameter": 4337.04,
      "gravity": 3.3320000000000003,
      "length_of_day": 19,
      "mass": 0,
      "type": "Carbide",
      "orbital_period": 9717.119998430353
    },
    {
      "position": {
        "x": -8510.884426005267,
        "y": 5587.937901175528
      },
      "name": "VII",
      "distance_from_parent": 1535445312.5,
      "diameter": 3189,
      "gravity": 4.704,
      "length_of_day": 23.9,
      "mass": 0,
      "type": "Super-Dense",
      "orbital_period": 12001.49845849047
    },
    {
      "position": {
        "x": -3741.3597785639226,
        "y": 14439.241731360156
      },
      "name": "VIII",
      "distance_from_parent": 2235818750,
      "diameter": 3316.56,
      "gravity": 3.724,
      "length_of_day": 25.5,
      "mass": 0,
      "type": "Metal",
      "orbital_period": 21088.167145976888
    }
  ]
}