{
  "name": "Zeta Corvi",
  "mass": 3e+24,
  "position": {
    "x": 8.3,
    "y": 997.9
  },
  "bodies": [
    {
      "position": {
        "x": 1386.4155151849893,
        "y": 2474.7735706151643
      },
      "name": "I",
      "distance_from_parent": 302998437.5,
      "diameter": 121309.56,
      "gravity": 18.62,
      "length_of_day": 9.9,
      "mass": 0,
      "orbital_period": 0
    },
    {
      "position": {
        "x": 4106.891300010126,
        "y": 3645.8000311960172
      },
      "name": "II",
      "distance_from_parent": 731929687.5,
      "diameter": 3571.6800000000003,
      "gravity": 0.784,
      "length_of_day": 28.1,
      "mass": 0,
      "orbital_period": 0
    },
    {
      "position": {
        "x": -1065.9598419832917,
        "y": -5227.1814643819
      },
      "name": "III",
      "distance_from_parent": 947564062.5,
      "diameter": 4464.599999999999,
      "gravity": 2.156,
      "length_of_day": 17.5,
      "mass": 0,
      "orbital_period": 0
    },
    {
      "position": {
        "x": -335.7812036319315,
        "y": 8668.874504452708
      },
      "name": "IV",
      "distance_from_parent": 1151803125,
      "diameter": 159067.32,
      "gravity": 24.402000000000005,
      "length_of_day": 10.5,
      "mass": 0,
      "orbital_period": 0
    },
    {
      "position": {
        "x": -5302.054835384341,
        "y": -4548.48379892398
      },
      "name": "IV-a",
      "distance_from_parent": 1151803125,
      "diameter": 3316.56,
      "gravity": 2.5480000000000005,
      "length_of_day": 24.5,
      "mass": 0,
      "orbital_period": 0
    },
    {
      "position": {
        "x": -5353.7423722082,
        "y": 6494.330052434044
      },
      "name": "IV-b",
      "distance_from_parent": 1151803125,
      "diameter": 3189,
      "gravity": 0.784,
      "length_of_day": 17.8,
      "mass": 0,
      "orbital_period": 0
    },
    {
      "position": {
        "x": -1960.3353290342668,
        "y": 8419.942620730117
      },
      "name": "IV-c",
      "distance_from_parent": 1151803125,
      "diameter": 4719.72,
      "gravity": 2.156,
      "length_of_day": 16.5,
      "mass": 0,
      "orbital_period": 0
    },
    {
      "position": {
        "x": -1849.8287183620498,
        "y": -10939.328124293857
      },
      "name": "V",
      "distance_from_parent": 1812146875,
      "diameter": 133810.44,
      "gravity": 20.482,
      "length_of_day": 11.8,
      "mass": 0,
      "orbital_period": 0
    },
    {
      "position": {
        "x": 6497.955258709523,
        "y": -9192.01816692057
      },
      "name": "V-a",
      "distance_from_parent": 1812146875,
      "diameter": 4464.599999999999,
      "gravity": 1.9600000000000002,
      "length_of_day": 29,
      "mass": 0,
      "orbital_period": 0
    },
    {
      "position": {
        "x": -2593.736969154727,
        "y": -10799.534519275201
      },
      "name": "V-b",
      "distance_from_parent": 1812146875,
      "diameter": 3571.6800000000003,
      "gravity": 5.586,
      "length_of_day": 26.3,
      "mass": 0,
      "orbital_period": 0
    },
    {
      "position": {
        "x": -11075.650146338723,
        "y": -3807.940902372015
      },
      "name": "V-c",
      "distance_from_parent": 1812146875,
      "diameter": 4081.92,
      "gravity": 1.764,
      "length_of_day": 15.8,
      "mass": 0,
      "orbital_period": 0
    },
    {
      "position": {
        "x": 9087.538205429448,
        "y": -6971.886147350774
      },
      "name": "V-d",
      "distance_from_parent": 1812146875,
      "diameter": 4592.16,
      "gravity": 1.078,
      "length_of_day": 18.2,
      "mass": 0,
      "orbital_period": 0
    },
    {
      "position": {
        "x": -12935.023979585938,
        "y": 4358.365390900249
      },
      "name": "VI",
      "distance_from_parent": 2005867187.5,
      "diameter": 122712.71999999999,
      "gravity": 19.796000000000003,
      "length_of_day": 11.9,
      "mass": 0,
      "orbital_period": 0
    },
    {
      "position": {
        "x": -13288.258969456656,
        "y": -424.7323684369218
      },
      "name": "VI-a",
      "distance_from_parent": 2005867187.5,
      "diameter": 4464.599999999999,
      "gravity": 3.3320000000000003,
      "length_of_day": 20.6,
      "mass": 0,
      "orbital_period": 0
    },
    {
      "position": {
        "x": -11444.066746609895,
        "y": -5906.132096181664
      },
      "name": "VI-b",
      "distance_from_parent": 2005867187.5,
      "diameter": 3826.7999999999997,
      "gravity": 5.978000000000001,
      "length_of_day": 15.6,
      "mass": 0,
      "orbital_period": 0
    },
    {
      "position": {
        "x": 3133.1856174331874,
        "y": 15972.310846192502
      },
      "name": "VII",
      "distance_from_parent": 2294548437.5,
      "diameter": 166210.68,
      "gravity": 25.480000000000004,
      "length_of_day": 11.8,
      "mass": 0,
      "orbital_period": 0
    },
    {
      "position": {
        "x": -12516.908476329854,
        "y": 9779.530995269804
      },
      "name": "VII-a",
      "distance_from_parent": 2294548437.5,
      "diameter": 3444.1200000000003,
      "gravity": 1.568,
      "length_of_day": 18.6,
      "mass": 0,
      "orbital_period": 0
    }
  ]
}